[{"id":458,"season":2014,"city":"Abu Dhabi","date":"16/04/14","team1":"Kolkata Knight Riders","team2":"Mumbai Indians","toss_winner":"Kolkata Knight Riders","toss_decision":"bat","result":"normal","dl_applied":0,"winner":"Kolkata Knight Riders","win_by_runs":41,"win_by_wickets":0,"player_of_match":"JH Kallis","venue":"Sheikh Zayed Stadium","umpire1":"M Erasmus","umpire2":"RK Illingworth","umpire3":""},{"id":459,"season":2014,"city":"Sharjah","date":"17/04/14","team1":"Delhi Daredevils","team2":"Royal Challengers Bangalore","toss_winner":"Royal Challengers Bangalore","toss_decision":"field","result":"normal","dl_applied":0,"winner":"Royal Challengers Bangalore","win_by_runs":0,"win_by_wickets":8,"player_of_match":"YS Chahal","venue":"Sharjah Cricket Stadium","umpire1":"Aleem Dar","umpire2":"S Ravi","umpire3":""},{"id":460,"season":2014,"city":"Abu Dhabi","date":"18/04/14","team1":"Chennai Super Kings","team2":"Kings XI Punjab","toss_winner":"Chennai Super Kings","toss_decision":"bat","result":"normal","dl_applied":0,"winner":"Kings XI Punjab","win_by_runs":0,"win_by_wickets":6,"player_of_match":"GJ Maxwell","venue":"Sheikh Zayed Stadium","umpire1":"RK Illingworth","umpire2":"C Shamshuddin","umpire3":""},{"id":461,"season":2014,"city":"Abu Dhabi","date":"18/04/14","team1":"Sunrisers Hyderabad","team2":"Rajasthan Royals","toss_winner":"Rajasthan Royals","toss_decision":"field","result":"normal","dl_applied":0,"winner":"Rajasthan Royals","win_by_runs":0,"win_by_wickets":4,"player_of_match":"AM Rahane","venue":"Sheikh Zayed Stadium","umpire1":"BF Bowden","umpire2":"RK Illingworth","umpire3":""},{"id":462,"season":2014,"city":"","date":"19/04/14","team1":"Mumbai Indians","team2":"Royal Challengers Bangalore","toss_winner":"Royal Challengers Bangalore","toss_decision":"field","result":"normal","dl_applied":0,"winner":"Royal Challengers Bangalore","win_by_runs":0,"win_by_wickets":7,"player_of_match":"PA Patel","venue":"Dubai International Cricket Stadium","umpire1":"Aleem Dar","umpire2":"AK Chaudhary","umpire3":""},{"id":463,"season":2014,"city":"","date":"19/04/14","team1":"Kolkata Knight Riders","team2":"Delhi Daredevils","toss_winner":"Kolkata Knight Riders","toss_decision":"bat","result":"normal","dl_applied":0,"winner":"Delhi Daredevils","win_by_runs":0,"win_by_wickets":4,"player_of_match":"JP Duminy","venue":"Dubai International Cricket Stadium","umpire1":"Aleem Dar","umpire2":"VA Kulkarni","umpire3":""},{"id":464,"season":2014,"city":"Sharjah","date":"20/04/14","team1":"Rajasthan Royals","team2":"Kings XI Punjab","toss_winner":"Kings XI Punjab","toss_decision":"field","result":"normal","dl_applied":0,"winner":"Kings XI Punjab","win_by_runs":0,"win_by_wickets":7,"player_of_match":"GJ Maxwell","venue":"Sharjah Cricket Stadium","umpire1":"BF Bowden","umpire2":"M Erasmus","umpire3":""},{"id":465,"season":2014,"city":"Abu Dhabi","date":"21/04/14","team1":"Chennai Super Kings","team2":"Delhi Daredevils","toss_winner":"Chennai Super Kings","toss_decision":"bat","result":"normal","dl_applied":0,"winner":"Chennai Super Kings","win_by_runs":93,"win_by_wickets":0,"player_of_match":"SK Raina","venue":"Sheikh Zayed Stadium","umpire1":"RK Illingworth","umpire2":"C Shamshuddin","umpire3":""},{"id":466,"season":2014,"city":"Sharjah","date":"22/04/14","team1":"Kings XI Punjab","team2":"Sunrisers Hyderabad","toss_winner":"Sunrisers Hyderabad","toss_decision":"field","result":"normal","dl_applied":0,"winner":"Kings XI Punjab","win_by_runs":72,"win_by_wickets":0,"player_of_match":"GJ Maxwell","venue":"Sharjah Cricket Stadium","umpire1":"M Erasmus","umpire2":"S Ravi","umpire3":""},{"id":467,"season":2014,"city":"","date":"23/04/14","team1":"Chennai Super Kings","team2":"Rajasthan Royals","toss_winner":"Rajasthan Royals","toss_decision":"field","result":"normal","dl_applied":0,"winner":"Chennai Super Kings","win_by_runs":7,"win_by_wickets":0,"player_of_match":"RA Jadeja","venue":"Dubai International Cricket Stadium","umpire1":"HDPK Dharmasena","umpire2":"RK Illingworth","umpire3":""},{"id":468,"season":2014,"city":"Sharjah","date":"24/04/14","team1":"Kolkata Knight Riders","team2":"Royal Challengers Bangalore","toss_winner":"Royal Challengers Bangalore","toss_decision":"field","result":"normal","dl_applied":0,"winner":"Kolkata Knight Riders","win_by_runs":2,"win_by_wickets":0,"player_of_match":"CA Lynn","venue":"Sharjah Cricket Stadium","umpire1":"Aleem Dar","umpire2":"VA Kulkarni","umpire3":""},{"id":469,"season":2014,"city":"","date":"25/04/14","team1":"Sunrisers Hyderabad","team2":"Delhi Daredevils","toss_winner":"Sunrisers Hyderabad","toss_decision":"bat","result":"normal","dl_applied":0,"winner":"Sunrisers Hyderabad","win_by_runs":4,"win_by_wickets":0,"player_of_match":"AJ Finch","venue":"Dubai International Cricket Stadium","umpire1":"M Erasmus","umpire2":"S Ravi","umpire3":""},{"id":470,"season":2014,"city":"","date":"25/04/14","team1":"Mumbai Indians","team2":"Chennai Super Kings","toss_winner":"Mumbai Indians","toss_decision":"bat","result":"normal","dl_applied":0,"winner":"Chennai Super Kings","win_by_runs":0,"win_by_wickets":7,"player_of_match":"MM Sharma","venue":"Dubai International Cricket Stadium","umpire1":"BF Bowden","umpire2":"M Erasmus","umpire3":""},{"id":471,"season":2014,"city":"Abu Dhabi","date":"26/04/14","team1":"Royal Challengers Bangalore","team2":"Rajasthan Royals","toss_winner":"Rajasthan Royals","toss_decision":"field","result":"normal","dl_applied":0,"winner":"Rajasthan Royals","win_by_runs":0,"win_by_wickets":6,"player_of_match":"PV Tambe","venue":"Sheikh Zayed Stadium","umpire1":"HDPK Dharmasena","umpire2":"C Shamshuddin","umpire3":""},{"id":472,"season":2014,"city":"Abu Dhabi","date":"26/04/14","team1":"Kings XI Punjab","team2":"Kolkata Knight Riders","toss_winner":"Kolkata Knight Riders","toss_decision":"field","result":"normal","dl_applied":0,"winner":"Kings XI Punjab","win_by_runs":23,"win_by_wickets":0,"player_of_match":"Sandeep Sharma","venue":"Sheikh Zayed Stadium","umpire1":"HDPK Dharmasena","umpire2":"RK Illingworth","umpire3":""},{"id":473,"season":2014,"city":"Sharjah","date":"27/04/14","team1":"Mumbai Indians","team2":"Delhi Daredevils","toss_winner":"Mumbai Indians","toss_decision":"bat","result":"normal","dl_applied":0,"winner":"Delhi Daredevils","win_by_runs":0,"win_by_wickets":6,"player_of_match":"M Vijay","venue":"Sharjah Cricket Stadium","umpire1":"Aleem Dar","umpire2":"VA Kulkarni","umpire3":""},{"id":474,"season":2014,"city":"Sharjah","date":"27/04/14","team1":"Sunrisers Hyderabad","team2":"Chennai Super Kings","toss_winner":"Sunrisers Hyderabad","toss_decision":"bat","result":"normal","dl_applied":0,"winner":"Chennai Super Kings","win_by_runs":0,"win_by_wickets":5,"player_of_match":"DR Smith","venue":"Sharjah Cricket Stadium","umpire1":"AK Chaudhary","umpire2":"VA Kulkarni","umpire3":""},{"id":475,"season":2014,"city":"","date":"28/04/14","team1":"Royal Challengers Bangalore","team2":"Kings XI Punjab","toss_winner":"Kings XI Punjab","toss_decision":"field","result":"normal","dl_applied":0,"winner":"Kings XI Punjab","win_by_runs":0,"win_by_wickets":5,"player_of_match":"Sandeep Sharma","venue":"Dubai International Cricket Stadium","umpire1":"BF Bowden","umpire2":"S Ravi","umpire3":""},{"id":476,"season":2014,"city":"Abu Dhabi","date":"29/04/14","team1":"Rajasthan Royals","team2":"Kolkata Knight Riders","toss_winner":"Rajasthan Royals","toss_decision":"bat","result":"tie","dl_applied":0,"winner":"Rajasthan Royals","win_by_runs":0,"win_by_wickets":0,"player_of_match":"JP Faulkner","venue":"Sheikh Zayed Stadium","umpire1":"Aleem Dar","umpire2":"AK Chaudhary","umpire3":""},{"id":477,"season":2014,"city":"","date":"30/04/14","team1":"Sunrisers Hyderabad","team2":"Mumbai Indians","toss_winner":"Mumbai Indians","toss_decision":"field","result":"normal","dl_applied":0,"winner":"Sunrisers Hyderabad","win_by_runs":15,"win_by_wickets":0,"player_of_match":"B Kumar","venue":"Dubai International Cricket Stadium","umpire1":"HDPK Dharmasena","umpire2":"M Erasmus","umpire3":""},{"id":478,"season":2014,"city":"Ranchi","date":"2/5/2014","team1":"Chennai Super Kings","team2":"Kolkata Knight Riders","toss_winner":"Chennai Super Kings","toss_decision":"bat","result":"normal","dl_applied":0,"winner":"Chennai Super Kings","win_by_runs":34,"win_by_wickets":0,"player_of_match":"RA Jadeja","venue":"JSCA International Stadium Complex","umpire1":"AK Chaudhary","umpire2":"NJ Llong","umpire3":""},{"id":479,"season":2014,"city":"Mumbai","date":"3/5/2014","team1":"Kings XI Punjab","team2":"Mumbai Indians","toss_winner":"Kings XI Punjab","toss_decision":"bat","result":"normal","dl_applied":0,"winner":"Mumbai Indians","win_by_runs":0,"win_by_wickets":5,"player_of_match":"CJ Anderson","venue":"Wankhede Stadium","umpire1":"BNJ Oxenford","umpire2":"C Shamshuddin","umpire3":""},{"id":480,"season":2014,"city":"Delhi","date":"3/5/2014","team1":"Delhi Daredevils","team2":"Rajasthan Royals","toss_winner":"Rajasthan Royals","toss_decision":"field","result":"normal","dl_applied":0,"winner":"Rajasthan Royals","win_by_runs":0,"win_by_wickets":7,"player_of_match":"KK Nair","venue":"Feroz Shah Kotla","umpire1":"SS Hazare","umpire2":"S Ravi","umpire3":""},{"id":481,"season":2014,"city":"Bangalore","date":"4/5/2014","team1":"Sunrisers Hyderabad","team2":"Royal Challengers Bangalore","toss_winner":"Royal Challengers Bangalore","toss_decision":"field","result":"normal","dl_applied":0,"winner":"Royal Challengers Bangalore","win_by_runs":0,"win_by_wickets":4,"player_of_match":"AB de Villiers","venue":"M Chinnaswamy Stadium","umpire1":"HDPK Dharmasena","umpire2":"VA Kulkarni","umpire3":""},{"id":482,"season":2014,"city":"Ahmedabad","date":"5/5/2014","team1":"Rajasthan Royals","team2":"Kolkata Knight Riders","toss_winner":"Kolkata Knight Riders","toss_decision":"field","result":"normal","dl_applied":0,"winner":"Rajasthan Royals","win_by_runs":10,"win_by_wickets":0,"player_of_match":"PV Tambe","venue":"Sardar Patel Stadium, Motera","umpire1":"NJ Llong","umpire2":"CK Nandan","umpire3":""},{"id":483,"season":2014,"city":"Delhi","date":"5/5/2014","team1":"Delhi Daredevils","team2":"Chennai Super Kings","toss_winner":"Chennai Super Kings","toss_decision":"field","result":"normal","dl_applied":0,"winner":"Chennai Super Kings","win_by_runs":0,"win_by_wickets":8,"player_of_match":"DR Smith","venue":"Feroz Shah Kotla","umpire1":"RM Deshpande","umpire2":"BNJ Oxenford","umpire3":""},{"id":484,"season":2014,"city":"Mumbai","date":"6/5/2014","team1":"Mumbai Indians","team2":"Royal Challengers Bangalore","toss_winner":"Royal Challengers Bangalore","toss_decision":"field","result":"normal","dl_applied":0,"winner":"Mumbai Indians","win_by_runs":19,"win_by_wickets":0,"player_of_match":"RG Sharma","venue":"Wankhede Stadium","umpire1":"S Ravi","umpire2":"K Srinath","umpire3":""},{"id":485,"season":2014,"city":"Delhi","date":"7/5/2014","team1":"Delhi Daredevils","team2":"Kolkata Knight Riders","toss_winner":"Delhi Daredevils","toss_decision":"bat","result":"normal","dl_applied":0,"winner":"Kolkata Knight Riders","win_by_runs":0,"win_by_wickets":8,"player_of_match":"G Gambhir","venue":"Feroz Shah Kotla","umpire1":"BNJ Oxenford","umpire2":"C Shamshuddin","umpire3":""},{"id":486,"season":2014,"city":"Cuttack","date":"7/5/2014","team1":"Kings XI Punjab","team2":"Chennai Super Kings","toss_winner":"Chennai Super Kings","toss_decision":"field","result":"normal","dl_applied":0,"winner":"Kings XI Punjab","win_by_runs":44,"win_by_wickets":0,"player_of_match":"GJ Maxwell","venue":"Barabati Stadium","umpire1":"HDPK Dharmasena","umpire2":"PG Pathak","umpire3":""},{"id":487,"season":2014,"city":"Ahmedabad","date":"8/5/2014","team1":"Sunrisers Hyderabad","team2":"Rajasthan Royals","toss_winner":"Rajasthan Royals","toss_decision":"field","result":"normal","dl_applied":0,"winner":"Sunrisers Hyderabad","win_by_runs":32,"win_by_wickets":0,"player_of_match":"B Kumar","venue":"Sardar Patel Stadium, Motera","umpire1":"AK Chaudhary","umpire2":"NJ Llong","umpire3":""},{"id":488,"season":2014,"city":"Bangalore","date":"9/5/2014","team1":"Kings XI Punjab","team2":"Royal Challengers Bangalore","toss_winner":"Royal Challengers Bangalore","toss_decision":"field","result":"normal","dl_applied":0,"winner":"Kings XI Punjab","win_by_runs":32,"win_by_wickets":0,"player_of_match":"Sandeep Sharma","venue":"M Chinnaswamy Stadium","umpire1":"S Ravi","umpire2":"K Srinath","umpire3":""},{"id":489,"season":2014,"city":"Delhi","date":"10/5/2014","team1":"Delhi Daredevils","team2":"Sunrisers Hyderabad","toss_winner":"Sunrisers Hyderabad","toss_decision":"field","result":"normal","dl_applied":1,"winner":"Sunrisers Hyderabad","win_by_runs":0,"win_by_wickets":8,"player_of_match":"DW Steyn","venue":"Feroz Shah Kotla","umpire1":"RM Deshpande","umpire2":"BNJ Oxenford","umpire3":""},{"id":490,"season":2014,"city":"Mumbai","date":"10/5/2014","team1":"Mumbai Indians","team2":"Chennai Super Kings","toss_winner":"Chennai Super Kings","toss_decision":"field","result":"normal","dl_applied":0,"winner":"Chennai Super Kings","win_by_runs":0,"win_by_wickets":4,"player_of_match":"DR Smith","venue":"Wankhede Stadium","umpire1":"HDPK Dharmasena","umpire2":"VA Kulkarni","umpire3":""},{"id":491,"season":2014,"city":"Cuttack","date":"11/5/2014","team1":"Kings XI Punjab","team2":"Kolkata Knight Riders","toss_winner":"Kolkata Knight Riders","toss_decision":"field","result":"normal","dl_applied":0,"winner":"Kolkata Knight Riders","win_by_runs":0,"win_by_wickets":9,"player_of_match":"G Gambhir","venue":"Barabati Stadium","umpire1":"NJ Llong","umpire2":"CK Nandan","umpire3":""},{"id":492,"season":2014,"city":"Bangalore","date":"11/5/2014","team1":"Royal Challengers Bangalore","team2":"Rajasthan Royals","toss_winner":"Royal Challengers Bangalore","toss_decision":"bat","result":"normal","dl_applied":0,"winner":"Rajasthan Royals","win_by_runs":0,"win_by_wickets":5,"player_of_match":"JP Faulkner","venue":"M Chinnaswamy Stadium","umpire1":"S Ravi","umpire2":"RJ Tucker","umpire3":""},{"id":493,"season":2014,"city":"Hyderabad","date":"12/5/2014","team1":"Sunrisers Hyderabad","team2":"Mumbai Indians","toss_winner":"Sunrisers Hyderabad","toss_decision":"bat","result":"normal","dl_applied":0,"winner":"Mumbai Indians","win_by_runs":0,"win_by_wickets":7,"player_of_match":"AT Rayudu","venue":"Rajiv Gandhi International Stadium, Uppal","umpire1":"HDPK Dharmasena","umpire2":"VA Kulkarni","umpire3":""},{"id":494,"season":2014,"city":"Ranchi","date":"13/05/14","team1":"Rajasthan Royals","team2":"Chennai Super Kings","toss_winner":"Rajasthan Royals","toss_decision":"bat","result":"normal","dl_applied":0,"winner":"Chennai Super Kings","win_by_runs":0,"win_by_wickets":5,"player_of_match":"RA Jadeja","venue":"JSCA International Stadium Complex","umpire1":"BNJ Oxenford","umpire2":"C Shamshuddin","umpire3":""},{"id":495,"season":2014,"city":"Bangalore","date":"13/05/14","team1":"Royal Challengers Bangalore","team2":"Delhi Daredevils","toss_winner":"Delhi Daredevils","toss_decision":"field","result":"normal","dl_applied":0,"winner":"Royal Challengers Bangalore","win_by_runs":16,"win_by_wickets":0,"player_of_match":"Yuvraj Singh","venue":"M Chinnaswamy Stadium","umpire1":"K Srinath","umpire2":"RJ Tucker","umpire3":""},{"id":496,"season":2014,"city":"Hyderabad","date":"14/05/14","team1":"Sunrisers Hyderabad","team2":"Kings XI Punjab","toss_winner":"Kings XI Punjab","toss_decision":"field","result":"normal","dl_applied":0,"winner":"Kings XI Punjab","win_by_runs":0,"win_by_wickets":6,"player_of_match":"WP Saha","venue":"Rajiv Gandhi International Stadium, Uppal","umpire1":"VA Kulkarni","umpire2":"PG Pathak","umpire3":""},{"id":497,"season":2014,"city":"Cuttack","date":"14/05/14","team1":"Mumbai Indians","team2":"Kolkata Knight Riders","toss_winner":"Kolkata Knight Riders","toss_decision":"field","result":"normal","dl_applied":0,"winner":"Kolkata Knight Riders","win_by_runs":0,"win_by_wickets":6,"player_of_match":"RV Uthappa","venue":"Barabati Stadium","umpire1":"AK Chaudhary","umpire2":"NJ Llong","umpire3":""},{"id":498,"season":2014,"city":"Ahmedabad","date":"15/05/14","team1":"Rajasthan Royals","team2":"Delhi Daredevils","toss_winner":"Delhi Daredevils","toss_decision":"field","result":"normal","dl_applied":0,"winner":"Rajasthan Royals","win_by_runs":62,"win_by_wickets":0,"player_of_match":"AM Rahane","venue":"Sardar Patel Stadium, Motera","umpire1":"S Ravi","umpire2":"RJ Tucker","umpire3":""},{"id":499,"season":2014,"city":"Ranchi","date":"18/05/14","team1":"Chennai Super Kings","team2":"Royal Challengers Bangalore","toss_winner":"Chennai Super Kings","toss_decision":"bat","result":"normal","dl_applied":0,"winner":"Royal Challengers Bangalore","win_by_runs":0,"win_by_wickets":5,"player_of_match":"AB de Villiers","venue":"JSCA International Stadium Complex","umpire1":"BNJ Oxenford","umpire2":"C Shamshuddin","umpire3":""},{"id":500,"season":2014,"city":"Hyderabad","date":"18/05/14","team1":"Sunrisers Hyderabad","team2":"Kolkata Knight Riders","toss_winner":"Sunrisers Hyderabad","toss_decision":"bat","result":"normal","dl_applied":0,"winner":"Kolkata Knight Riders","win_by_runs":0,"win_by_wickets":7,"player_of_match":"UT Yadav","venue":"Rajiv Gandhi International Stadium, Uppal","umpire1":"NJ Llong","umpire2":"CK Nandan","umpire3":""},{"id":501,"season":2014,"city":"Ahmedabad","date":"19/05/14","team1":"Mumbai Indians","team2":"Rajasthan Royals","toss_winner":"Mumbai Indians","toss_decision":"bat","result":"normal","dl_applied":0,"winner":"Mumbai Indians","win_by_runs":25,"win_by_wickets":0,"player_of_match":"MEK Hussey","venue":"Sardar Patel Stadium, Motera","umpire1":"S Ravi","umpire2":"RJ Tucker","umpire3":""},{"id":502,"season":2014,"city":"Delhi","date":"19/05/14","team1":"Delhi Daredevils","team2":"Kings XI Punjab","toss_winner":"Kings XI Punjab","toss_decision":"field","result":"normal","dl_applied":0,"winner":"Kings XI Punjab","win_by_runs":0,"win_by_wickets":4,"player_of_match":"AR Patel","venue":"Feroz Shah Kotla","umpire1":"HDPK Dharmasena","umpire2":"PG Pathak","umpire3":""},{"id":503,"season":2014,"city":"Hyderabad","date":"20/05/14","team1":"Royal Challengers Bangalore","team2":"Sunrisers Hyderabad","toss_winner":"Royal Challengers Bangalore","toss_decision":"bat","result":"normal","dl_applied":0,"winner":"Sunrisers Hyderabad","win_by_runs":0,"win_by_wickets":7,"player_of_match":"DA Warner","venue":"Rajiv Gandhi International Stadium, Uppal","umpire1":"AK Chaudhary","umpire2":"NJ Llong","umpire3":""},{"id":504,"season":2014,"city":"Kolkata","date":"20/05/14","team1":"Chennai Super Kings","team2":"Kolkata Knight Riders","toss_winner":"Kolkata Knight Riders","toss_decision":"field","result":"normal","dl_applied":0,"winner":"Kolkata Knight Riders","win_by_runs":0,"win_by_wickets":8,"player_of_match":"RV Uthappa","venue":"Eden Gardens","umpire1":"RM Deshpande","umpire2":"C Shamshuddin","umpire3":""},{"id":505,"season":2014,"city":"Chandigarh","date":"21/05/14","team1":"Kings XI Punjab","team2":"Mumbai Indians","toss_winner":"Mumbai Indians","toss_decision":"field","result":"normal","dl_applied":0,"winner":"Mumbai Indians","win_by_runs":0,"win_by_wickets":7,"player_of_match":"LMP Simmons","venue":"Punjab Cricket Association Stadium, Mohali","umpire1":"HDPK Dharmasena","umpire2":"VA Kulkarni","umpire3":""},{"id":506,"season":2014,"city":"Kolkata","date":"22/05/14","team1":"Kolkata Knight Riders","team2":"Royal Challengers Bangalore","toss_winner":"Royal Challengers Bangalore","toss_decision":"field","result":"normal","dl_applied":0,"winner":"Kolkata Knight Riders","win_by_runs":30,"win_by_wickets":0,"player_of_match":"RV Uthappa","venue":"Eden Gardens","umpire1":"AK Chaudhary","umpire2":"CK Nandan","umpire3":""},{"id":507,"season":2014,"city":"Ranchi","date":"22/05/14","team1":"Chennai Super Kings","team2":"Sunrisers Hyderabad","toss_winner":"Sunrisers Hyderabad","toss_decision":"field","result":"normal","dl_applied":0,"winner":"Sunrisers Hyderabad","win_by_runs":0,"win_by_wickets":6,"player_of_match":"DA Warner","venue":"JSCA International Stadium Complex","umpire1":"BNJ Oxenford","umpire2":"C Shamshuddin","umpire3":""},{"id":508,"season":2014,"city":"Mumbai","date":"23/05/14","team1":"Mumbai Indians","team2":"Delhi Daredevils","toss_winner":"Delhi Daredevils","toss_decision":"field","result":"normal","dl_applied":0,"winner":"Mumbai Indians","win_by_runs":15,"win_by_wickets":0,"player_of_match":"MEK Hussey","venue":"Wankhede Stadium","umpire1":"S Ravi","umpire2":"RJ Tucker","umpire3":""},{"id":509,"season":2014,"city":"Chandigarh","date":"23/05/14","team1":"Kings XI Punjab","team2":"Rajasthan Royals","toss_winner":"Rajasthan Royals","toss_decision":"field","result":"normal","dl_applied":0,"winner":"Kings XI Punjab","win_by_runs":16,"win_by_wickets":0,"player_of_match":"SE Marsh","venue":"Punjab Cricket Association Stadium, Mohali","umpire1":"HDPK Dharmasena","umpire2":"PG Pathak","umpire3":""},{"id":510,"season":2014,"city":"Bangalore","date":"24/05/14","team1":"Royal Challengers Bangalore","team2":"Chennai Super Kings","toss_winner":"Chennai Super Kings","toss_decision":"field","result":"normal","dl_applied":0,"winner":"Chennai Super Kings","win_by_runs":0,"win_by_wickets":8,"player_of_match":"MS Dhoni","venue":"M Chinnaswamy Stadium","umpire1":"AK Chaudhary","umpire2":"NJ Llong","umpire3":""},{"id":511,"season":2014,"city":"Kolkata","date":"24/05/14","team1":"Sunrisers Hyderabad","team2":"Kolkata Knight Riders","toss_winner":"Kolkata Knight Riders","toss_decision":"field","result":"normal","dl_applied":0,"winner":"Kolkata Knight Riders","win_by_runs":0,"win_by_wickets":4,"player_of_match":"YK Pathan","venue":"Eden Gardens","umpire1":"RM Deshpande","umpire2":"BNJ Oxenford","umpire3":""},{"id":512,"season":2014,"city":"Chandigarh","date":"25/05/14","team1":"Delhi Daredevils","team2":"Kings XI Punjab","toss_winner":"Kings XI Punjab","toss_decision":"field","result":"normal","dl_applied":0,"winner":"Kings XI Punjab","win_by_runs":0,"win_by_wickets":7,"player_of_match":"M Vohra","venue":"Punjab Cricket Association Stadium, Mohali","umpire1":"HDPK Dharmasena","umpire2":"VA Kulkarni","umpire3":""},{"id":513,"season":2014,"city":"Mumbai","date":"25/05/14","team1":"Rajasthan Royals","team2":"Mumbai Indians","toss_winner":"Mumbai Indians","toss_decision":"field","result":"normal","dl_applied":0,"winner":"Mumbai Indians","win_by_runs":0,"win_by_wickets":5,"player_of_match":"CJ Anderson","venue":"Wankhede Stadium","umpire1":"K Srinath","umpire2":"RJ Tucker","umpire3":""},{"id":514,"season":2014,"city":"Kolkata","date":"27/05/14","team1":"Kolkata Knight Riders","team2":"Kings XI Punjab","toss_winner":"Kings XI Punjab","toss_decision":"field","result":"normal","dl_applied":0,"winner":"Kolkata Knight Riders","win_by_runs":28,"win_by_wickets":0,"player_of_match":"UT Yadav","venue":"Eden Gardens","umpire1":"NJ Llong","umpire2":"S Ravi","umpire3":""},{"id":515,"season":2014,"city":"Mumbai","date":"28/05/14","team1":"Mumbai Indians","team2":"Chennai Super Kings","toss_winner":"Chennai Super Kings","toss_decision":"field","result":"normal","dl_applied":0,"winner":"Chennai Super Kings","win_by_runs":0,"win_by_wickets":7,"player_of_match":"SK Raina","venue":"Brabourne Stadium","umpire1":"VA Kulkarni","umpire2":"BNJ Oxenford","umpire3":""},{"id":516,"season":2014,"city":"Mumbai","date":"30/05/14","team1":"Kings XI Punjab","team2":"Chennai Super Kings","toss_winner":"Chennai Super Kings","toss_decision":"field","result":"normal","dl_applied":0,"winner":"Kings XI Punjab","win_by_runs":24,"win_by_wickets":0,"player_of_match":"V Sehwag","venue":"Wankhede Stadium","umpire1":"HDPK Dharmasena","umpire2":"RJ Tucker","umpire3":""},{"id":517,"season":2014,"city":"Bangalore","date":"1/6/2014","team1":"Kings XI Punjab","team2":"Kolkata Knight Riders","toss_winner":"Kolkata Knight Riders","toss_decision":"field","result":"normal","dl_applied":0,"winner":"Kolkata Knight Riders","win_by_runs":0,"win_by_wickets":3,"player_of_match":"MK Pandey","venue":"M Chinnaswamy Stadium","umpire1":"HDPK Dharmasena","umpire2":"BNJ Oxenford","umpire3":""}]